SpringBootCankaoZhinan/README.md
SpringBootCankaoZhinan/__init__.py
SpringBootCankaoZhinan/__main__.py
SpringBootCankaoZhinan/file.epub
SpringBootCankaoZhinan/index.html
SpringBootCankaoZhinan/css/__init__.py
SpringBootCankaoZhinan/css/annotations.css
SpringBootCankaoZhinan/css/main.css
SpringBootCankaoZhinan/css/normalize.css
SpringBootCankaoZhinan/css/popup.css
SpringBootCankaoZhinan/font/__init__.py
SpringBootCankaoZhinan/font/fontello.eot
SpringBootCankaoZhinan/font/fontello.svg
SpringBootCankaoZhinan/font/fontello.ttf
SpringBootCankaoZhinan/font/fontello.woff
SpringBootCankaoZhinan/img/__init__.py
SpringBootCankaoZhinan/img/annotator-glyph-sprite.png
SpringBootCankaoZhinan/img/annotator-icon-sprite.png
SpringBootCankaoZhinan/img/apple-touch-icon.png
SpringBootCankaoZhinan/img/cancelfullscreen.png
SpringBootCankaoZhinan/img/close.png
SpringBootCankaoZhinan/img/fullscreen.png
SpringBootCankaoZhinan/img/loader.gif
SpringBootCankaoZhinan/img/menu-icon.png
SpringBootCankaoZhinan/img/save.png
SpringBootCankaoZhinan/img/saved.png
SpringBootCankaoZhinan/img/settings-s.png
SpringBootCankaoZhinan/img/settings.png
SpringBootCankaoZhinan/img/star.png
SpringBootCankaoZhinan/js/__init__.py
SpringBootCankaoZhinan/js/epub.js
SpringBootCankaoZhinan/js/epub.min.js
SpringBootCankaoZhinan/js/epub.min.map
SpringBootCankaoZhinan/js/hooks.min.js
SpringBootCankaoZhinan/js/hooks.min.map
SpringBootCankaoZhinan/js/reader.js
SpringBootCankaoZhinan/js/reader.js.map
SpringBootCankaoZhinan/js/reader.min.js
SpringBootCankaoZhinan/js/reader.min.map
SpringBootCankaoZhinan/js/hooks/__init__.py
SpringBootCankaoZhinan/js/hooks/extensions/__init__.py
SpringBootCankaoZhinan/js/hooks/extensions/highlight.js
SpringBootCankaoZhinan/js/libs/__init__.py
SpringBootCankaoZhinan/js/libs/jquery.min.js
SpringBootCankaoZhinan/js/libs/localforage.min.js
SpringBootCankaoZhinan/js/libs/screenfull.js
SpringBootCankaoZhinan/js/libs/screenfull.min.js
SpringBootCankaoZhinan/js/libs/zip.min.js
spring_boot_cankao_zhinan-2024.3.2.0.dist-info/METADATA
spring_boot_cankao_zhinan-2024.3.2.0.dist-info/WHEEL
spring_boot_cankao_zhinan-2024.3.2.0.dist-info/entry_points.txt
spring_boot_cankao_zhinan-2024.3.2.0.dist-info/top_level.txt
spring_boot_cankao_zhinan-2024.3.2.0.dist-info/RECORD
